[
  {
    "name": "Criss Cross Contrast Binding Cami Top",
    "price": "5,00",
    "url": "https://eur.shein.com/Criss-Cross-Contrast-Binding-Cami-Top-p-2969033-cat-1779.html?scici=Search~~EditSearch~~1~~top~~~~0"
  },
  {
    "name": "Solid Hanky Hem Tube Top",
    "price": "8,00",
    "url": "https://eur.shein.com/Solid-Hanky-Hem-Tube-Top-p-2745052-cat-2223.html?scici=Search~~EditSearch~~1~~top~~~~0"
  },
  {
    "name": "Rib-Knit Crop Halter Top",
    "price": "5,00",
    "url": "https://eur.shein.com/Rib-Knit-Crop-Halter-Top-p-2844079-cat-1779.html?scici=Search~~EditSearch~~1~~top~~~~0"
  },
  {
    "name": "SHEIN 4pcs Solid Ribbed Knit Crop Top",
    "price": "15,00",
    "url": "https://eur.shein.com/SHEIN-4pcs-Solid-Ribbed-Knit-Crop-Top-p-6968452-cat-2223.html?scici=Search~~EditSearch~~1~~top~~~~0"
  },
  {
    "name": "Appliques Zipper Detail Cami Top",
    "price": "8,00 9,00",
    "url": "https://eur.shein.com/Appliques-Zipper-Detail-Cami-Top-p-2357899-cat-1779.html?scici=Search~~EditSearch~~1~~top~~~~0"
  },
  {
    "name": "Crisscross Back Contrast Binding Cami Top",
    "price": "5,00",
    "url": "https://eur.shein.com/Crisscross-Back-Contrast-Binding-Cami-Top-p-2865825-cat-1779.html?scici=Search~~EditSearch~~1~~top~~~~0"
  },
  {
    "name": "Guipure Lace Crop Cami Top",
    "price": "7,00",
    "url": "https://eur.shein.com/Guipure-Lace-Crop-Cami-Top-p-4989312-cat-1779.html?scici=Search~~EditSearch~~1~~top~~~~0"
  },
  {
    "name": "SHEIN SXY Draped Collar Crisscross Back Satin Cami Top",
    "price": "4,00 7,00",
    "url": "https://eur.shein.com/SHEIN-SXY-Draped-Collar-Crisscross-Back-Satin-Cami-Top-p-5873667-cat-1779.html?scici=Search~~EditSearch~~1~~top~~~~0"
  },
  {
    "name": "SHEIN Tie Front Ruched Bust Frilled Cami Top",
    "price": "5,00",
    "url": "https://eur.shein.com/SHEIN-Tie-Front-Ruched-Bust-Frilled-Cami-Top-p-2334597-cat-1779.html?scici=Search~~EditSearch~~1~~top~~~~0"
  },
  {
    "name": "Letter Graphic Sheer Mesh Crop Top",
    "price": "4,00",
    "url": "https://eur.shein.com/Letter-Graphic-Sheer-Mesh-Crop-Top-p-3098124-cat-2223.html?scici=Search~~EditSearch~~1~~top~~~~0"
  },
  {
    "name": "SHEIN PETITE Tie Back Asymmetrical Hem Cami Top",
    "price": "3,00",
    "url": "https://eur.shein.com/SHEIN-PETITE-Tie-Back-Asymmetrical-Hem-Cami-Top-p-7021312-cat-1779.html?scici=Search~~EditSearch~~1~~top~~~~0"
  },
  {
    "name": "Two Tone Crossover Front Cami Top",
    "price": "5,00",
    "url": "https://eur.shein.com/Two-Tone-Crossover-Front-Cami-Top-p-2219034-cat-1779.html?scici=Search~~EditSearch~~1~~top~~~~0"
  },
  {
    "name": "Notch Neck Solid Cami Crop Top",
    "price": "6,00",
    "url": "https://eur.shein.com/Notch-Neck-Solid-Cami-Crop-Top-p-2074390-cat-1779.html?scici=Search~~EditSearch~~1~~top~~~~0"
  },
  {
    "name": "Draped Bandana Hem Crop Cami Top",
    "price": "4,00",
    "url": "https://eur.shein.com/Draped-Bandana-Hem-Crop-Cami-Top-p-6865992-cat-1779.html?scici=Search~~EditSearch~~1~~top~~~~0"
  },
  {
    "name": "SHEIN SXY Half Button Crop Cami Top",
    "price": "6,00",
    "url": "https://eur.shein.com/SHEIN-SXY-Half-Button-Crop-Cami-Top-p-3002502-cat-1779.html?scici=Search~~EditSearch~~1~~top~~~~0"
  },
  {
    "name": "V Back Lace Trim Cami Top",
    "price": "7,00",
    "url": "https://eur.shein.com/V-Back-Lace-Trim-Cami-Top-p-3176995-cat-1779.html?scici=Search~~EditSearch~~1~~top~~~~0"
  },
  {
    "name": "Nailea X SHEINsquad Rib-knit Crop Top",
    "price": "3,99",
    "url": "https://eur.shein.com/Nailea-X-SHEINsquad-Rib-knit-Crop-Top-p-2544773-cat-1738.html?scici=Search~~EditSearch~~1~~top~~~~0"
  },
  {
    "name": "Solid Drawstring Side Crop Cami Top",
    "price": "6,00",
    "url": "https://eur.shein.com/Solid-Drawstring-Side-Crop-Cami-Top-p-2881129-cat-1779.html?scici=Search~~EditSearch~~1~~top~~~~0"
  },
  {
    "name": "SHEIN Letter Graphic Ringer Tank Top",
    "price": "6,00",
    "url": "https://eur.shein.com/SHEIN-Letter-Graphic-Ringer-Tank-Top-p-2533624-cat-1779.html?scici=Search~~EditSearch~~1~~top~~~~0"
  },
  {
    "name": "SHEIN SXY Solid One Shoulder Top",
    "price": "5,00",
    "url": "https://eur.shein.com/SHEIN-SXY-Solid-One-Shoulder-Top-p-3243568-cat-2223.html?scici=Search~~EditSearch~~1~~top~~~~0"
  },
  {
    "name": "Backless Lace Up Crop Cami Top",
    "price": "6,00",
    "url": "https://eur.shein.com/Backless-Lace-Up-Crop-Cami-Top-p-6324082-cat-1779.html?scici=Search~~EditSearch~~1~~top~~~~0"
  },
  {
    "name": "Contrast Lace Crop Cami Top",
    "price": "7,00",
    "url": "https://eur.shein.com/Contrast-Lace-Crop-Cami-Top-p-3477507-cat-1779.html?scici=Search~~EditSearch~~1~~top~~~~0"
  },
  {
    "name": "Marble Print Drawstring Asymmetrical Hem Crop Top",
    "price": "8,00",
    "url": "https://eur.shein.com/Marble-Print-Drawstring-Asymmetrical-Hem-Crop-Top-p-3530211-cat-2223.html?scici=Search~~EditSearch~~1~~top~~~~0"
  },
  {
    "name": "Lace Up Back Flounce Sleeve Hanky Hem Crop Top",
    "price": "12,00",
    "url": "https://eur.shein.com/Lace-Up-Back-Flounce-Sleeve-Hanky-Hem-Crop-Top-p-4655647-cat-2223.html?scici=Search~~EditSearch~~1~~top~~~~0"
  },
  {
    "name": "Crisscross Tied Backless Rib Knit Crop Top",
    "price": "8,00",
    "url": "https://eur.shein.com/Crisscross-Tied-Backless-Rib-Knit-Crop-Top-p-2606473-cat-1779.html?scici=Search~~EditSearch~~1~~top~~~~0"
  },
  {
    "name": "SHEIN Cutout Front Crop Tank Top",
    "price": "6,00",
    "url": "https://eur.shein.com/SHEIN-Cutout-Front-Crop-Tank-Top-p-4531361-cat-1779.html?scici=Search~~EditSearch~~1~~top~~~~0"
  },
  {
    "name": "One Shoulder Cut Out Ribbed Crop Top",
    "price": "5,00",
    "url": "https://eur.shein.com/One-Shoulder-Cut-Out-Ribbed-Crop-Top-p-2745300-cat-2223.html?scici=Search~~EditSearch~~1~~top~~~~0"
  },
  {
    "name": "Ruched Asymmetric Hem Lace Top",
    "price": "7,00 10,00",
    "url": "https://eur.shein.com/Ruched-Asymmetric-Hem-Lace-Top-p-3166231-cat-2223.html?scici=Search~~EditSearch~~1~~top~~~~0"
  },
  {
    "name": "SHEIN Solid Fitted Crop Top",
    "price": "3,99",
    "url": "https://eur.shein.com/SHEIN-Solid-Fitted-Crop-Top-p-1411465-cat-1738.html?scici=Search~~EditSearch~~1~~top~~~~0"
  },
  {
    "name": "SHEIN Lace Trim Halter Crop Top",
    "price": "4,00",
    "url": "https://eur.shein.com/SHEIN-Lace-Trim-Halter-Crop-Top-p-2747109-cat-1779.html?scici=Search~~EditSearch~~1~~top~~~~0"
  },
  {
    "name": "Contrast Lace Crop Cami Top",
    "price": "7,00",
    "url": "https://eur.shein.com/Contrast-Lace-Crop-Cami-Top-p-2642297-cat-1779.html?scici=Search~~EditSearch~~1~~top~~~~0"
  },
  {
    "name": "SHEIN Floral and Graphic Print Cami Top",
    "price": "5,00",
    "url": "https://eur.shein.com/SHEIN-Floral-and-Graphic-Print-Cami-Top-p-2096861-cat-1779.html?scici=Search~~EditSearch~~1~~top~~~~0"
  },
  {
    "name": "Solid Flounce Sleeve Tie Front Ribbed Knit Top",
    "price": "7,00 8,99",
    "url": "https://eur.shein.com/Solid-Flounce-Sleeve-Tie-Front-Ribbed-Knit-Top-p-6910267-cat-1738.html?scici=Search~~EditSearch~~1~~top~~~~0"
  },
  {
    "name": "Sweetheart Neck Lantern Sleeve Crop Top",
    "price": "11,00",
    "url": "https://eur.shein.com/Sweetheart-Neck-Lantern-Sleeve-Crop-Top-p-6682802-cat-2223.html?scici=Search~~EditSearch~~1~~top~~~~0"
  },
  {
    "name": "Lace Up Backless Butterfly Embroidered Cami Top",
    "price": "7,00",
    "url": "https://eur.shein.com/Lace-Up-Backless-Butterfly-Embroidered-Cami-Top-p-3421927-cat-1779.html?scici=Search~~EditSearch~~1~~top~~~~0"
  },
  {
    "name": "DAZY Graphic Print Tank Top",
    "price": "6,00",
    "url": "https://eur.shein.com/DAZY-Graphic-Print-Tank-Top-p-5219012-cat-1779.html?scici=Search~~EditSearch~~1~~top~~~~0"
  },
  {
    "name": "4pcs Rib-knit Top",
    "price": "16,00",
    "url": "https://eur.shein.com/4pcs-Rib-knit-Top-p-5673977-cat-1779.html?scici=Search~~EditSearch~~1~~top~~~~0"
  },
  {
    "name": "SHEIN Crisscross Tie Back Crop Tank Top",
    "price": "5,00",
    "url": "https://eur.shein.com/SHEIN-Crisscross-Tie-Back-Crop-Tank-Top-p-2342231-cat-1779.html?scici=Search~~EditSearch~~1~~top~~~~0"
  },
  {
    "name": "Square Neck Flounce Sleeve Tie Back Crop Milkmaid Blouse",
    "price": "14,00",
    "url": "https://eur.shein.com/Square-Neck-Flounce-Sleeve-Tie-Back-Crop-Milkmaid-Blouse-p-3420509-cat-1733.html?scici=Search~~EditSearch~~1~~top~~~~0"
  },
  {
    "name": "SHEIN Puff Sleeve Ruched Bust Crop Top",
    "price": "3,99",
    "url": "https://eur.shein.com/SHEIN-Puff-Sleeve-Ruched-Bust-Crop-Top-p-2475509-cat-1738.html?scici=Search~~EditSearch~~1~~top~~~~0"
  },
  {
    "name": "Solid Cross Crop Halter Top",
    "price": "5,00",
    "url": "https://eur.shein.com/Solid-Cross-Crop-Halter-Top-p-2178605-cat-1779.html?scici=Search~~EditSearch~~1~~top~~~~0"
  },
  {
    "name": "Ruffle Trim Round Neck Rib-knit Top",
    "price": "7,00",
    "url": "https://eur.shein.com/Ruffle-Trim-Round-Neck-Rib-knit-Top-p-3039267-cat-1738.html?scici=Search~~EditSearch~~1~~top~~~~0"
  },
  {
    "name": "Floral Print Backless Rib Knit Halter Crop Top",
    "price": "5,00",
    "url": "https://eur.shein.com/Floral-Print-Backless-Rib-Knit-Halter-Crop-Top-p-2477068-cat-1779.html?scici=Search~~EditSearch~~1~~top~~~~0"
  },
  {
    "name": "Knot Front Flounce Sleeve Crop Chiffon Top",
    "price": "9,00",
    "url": "https://eur.shein.com/Knot-Front-Flounce-Sleeve-Crop-Chiffon-Top-p-3297253-cat-2223.html?scici=Search~~EditSearch~~1~~top~~~~0"
  },
  {
    "name": "SHEIN Lace Trim Knotted Sheer Embroidery Mesh Top Without Camisole",
    "price": "2,99 4,00",
    "url": "https://eur.shein.com/SHEIN-Lace-Trim-Knotted-Sheer-Embroidery-Mesh-Top-Without-Camisole-p-2150230-cat-2223.html?scici=Search~~EditSearch~~1~~top~~~~0"
  },
  {
    "name": "SHEIN Rhinestone Butterfly Front Top",
    "price": "3,49 4,99",
    "url": "https://eur.shein.com/SHEIN-Rhinestone-Butterfly-Front-Top-p-2189969-cat-1738.html?scici=Search~~EditSearch~~1~~top~~~~0"
  },
  {
    "name": "SHEIN Notched Neck Rib-knit Tank Top",
    "price": "4,00",
    "url": "https://eur.shein.com/SHEIN-Notched-Neck-Rib-knit-Tank-Top-p-1411595-cat-1779.html?scici=Search~~EditSearch~~1~~top~~~~0"
  },
  {
    "name": "SHEIN Solid Rib-knit Cami Top",
    "price": "4,00",
    "url": "https://eur.shein.com/SHEIN-Solid-Rib-knit-Cami-Top-p-2459946-cat-1779.html?scici=Search~~EditSearch~~1~~top~~~~0"
  },
  {
    "name": "Letter & Graphic Embroidery Rib-knit Tank Top",
    "price": "6,00",
    "url": "https://eur.shein.com/Letter-Graphic-Embroidery-Rib-knit-Tank-Top-p-3721046-cat-1779.html?scici=Search~~EditSearch~~1~~top~~~~0"
  },
  {
    "name": "SHEIN Lettuce Trim Solid Mesh Top",
    "price": "6,00",
    "url": "https://eur.shein.com/SHEIN-Lettuce-Trim-Solid-Mesh-Top-p-2838708-cat-2223.html?scici=Search~~EditSearch~~1~~top~~~~0"
  },
  {
    "name": "SHEIN Crisscross Tied Backless Hanky Hem Cami Top",
    "price": "3,00",
    "url": "https://eur.shein.com/SHEIN-Crisscross-Tied-Backless-Hanky-Hem-Cami-Top-p-7024522-cat-1779.html?scici=Search~~EditSearch~~1~~top~~~~0"
  },
  {
    "name": "SHEIN Ruched Drawstring Side Heart Top",
    "price": "4,99",
    "url": "https://eur.shein.com/SHEIN-Ruched-Drawstring-Side-Heart-Top-p-3361517-cat-1738.html?scici=Search~~EditSearch~~1~~top~~~~0"
  },
  {
    "name": "3pcs Solid Backless Halter Top",
    "price": "13,00",
    "url": "https://eur.shein.com/3pcs-Solid-Backless-Halter-Top-p-3224659-cat-1779.html?scici=Search~~EditSearch~~1~~top~~~~0"
  },
  {
    "name": "SHEIN Form-Fitting Crisscross Halter Top",
    "price": "4,00",
    "url": "https://eur.shein.com/SHEIN-Form-Fitting-Crisscross-Halter-Top-p-3563031-cat-1779.html?scici=Search~~EditSearch~~1~~top~~~~0"
  },
  {
    "name": "SHEIN Notched Neck Lettuce Trim Tank Top",
    "price": "4,00",
    "url": "https://eur.shein.com/SHEIN-Notched-Neck-Lettuce-Trim-Tank-Top-p-2221220-cat-1779.html?scici=Search~~EditSearch~~1~~top~~~~0"
  },
  {
    "name": "SHEIN Tie Back Rib-knit Top",
    "price": "3,99",
    "url": "https://eur.shein.com/SHEIN-Tie-Back-Rib-knit-Top-p-1715478-cat-1738.html?scici=Search~~EditSearch~~1~~top~~~~0"
  },
  {
    "name": "Rib-knit Solid Crop Tank Top",
    "price": "5,00",
    "url": "https://eur.shein.com/Rib-knit-Solid-Crop-Tank-Top-p-3085575-cat-1779.html?scici=Search~~EditSearch~~1~~top~~~~0"
  },
  {
    "name": "Puff Sleeve Tied Backless Crop Top",
    "price": "7,00",
    "url": "https://eur.shein.com/Puff-Sleeve-Tied-Backless-Crop-Top-p-2422685-cat-1733.html?scici=Search~~EditSearch~~1~~top~~~~0"
  },
  {
    "name": "SHEIN Asymmetrical Hem Rib-knit Crop Tank Top",
    "price": "5,00",
    "url": "https://eur.shein.com/SHEIN-Asymmetrical-Hem-Rib-knit-Crop-Tank-Top-p-2223333-cat-1779.html?scici=Search~~EditSearch~~1~~top~~~~0"
  },
  {
    "name": "Draped Front Tank Top",
    "price": "6,00",
    "url": "https://eur.shein.com/Draped-Front-Tank-Top-p-2549097-cat-1779.html?scici=Search~~EditSearch~~1~~top~~~~0"
  },
  {
    "name": "Letter Graphic Tank Top",
    "price": "4,00",
    "url": "https://eur.shein.com/Letter-Graphic-Tank-Top-p-5738007-cat-1779.html?scici=Search~~EditSearch~~1~~top~~~~0"
  },
  {
    "name": "SHEIN Eagle & Letter Graphic Crop Top",
    "price": "3,99 4,99",
    "url": "https://eur.shein.com/SHEIN-Eagle-Letter-Graphic-Crop-Top-p-3091950-cat-1738.html?scici=Search~~EditSearch~~1~~top~~~~0"
  },
  {
    "name": "4pcs Rib-knit Top",
    "price": "15,00",
    "url": "https://eur.shein.com/4pcs-Rib-knit-Top-p-7138282-cat-2223.html?scici=Search~~EditSearch~~1~~top~~~~0"
  },
  {
    "name": "SHEIN SXY Ring Linked Tie Backless 2 In 1 Crop Top",
    "price": "7,00",
    "url": "https://eur.shein.com/SHEIN-SXY-Ring-Linked-Tie-Backless-2-In-1-Crop-Top-p-7629847-cat-1779.html?scici=Search~~EditSearch~~1~~top~~~~0"
  },
  {
    "name": "Tied Backless Wrap Cross Crop Halter Top",
    "price": "5,00 6,00",
    "url": "https://eur.shein.com/Tied-Backless-Wrap-Cross-Crop-Halter-Top-p-5732897-cat-1779.html?scici=Search~~EditSearch~~1~~top~~~~0"
  },
  {
    "name": "Cut Out Twist Hem Tank Top",
    "price": "11,00",
    "url": "https://eur.shein.com/Cut-Out-Twist-Hem-Tank-Top-p-7778282-cat-1779.html?scici=Search~~EditSearch~~1~~top~~~~0"
  },
  {
    "name": "SHEIN SXY Solid Plunging Neck Cross Top",
    "price": "3,99",
    "url": "https://eur.shein.com/SHEIN-SXY-Solid-Plunging-Neck-Cross-Top-p-4071076-cat-1738.html?scici=Search~~EditSearch~~1~~top~~~~0"
  },
  {
    "name": "SHEIN SXY Butterfly Chain Front Top",
    "price": "9,00",
    "url": "https://eur.shein.com/SHEIN-SXY-Butterfly-Chain-Front-Top-p-3270505-cat-1738.html?scici=Search~~EditSearch~~1~~top~~~~0"
  },
  {
    "name": "Slogan Graphic Contrast Binding Tank Top",
    "price": "5,00",
    "url": "https://eur.shein.com/Slogan-Graphic-Contrast-Binding-Tank-Top-p-4990602-cat-1779.html?scici=Search~~EditSearch~~1~~top~~~~0"
  },
  {
    "name": "SHEIN SXY Cold Shoulder Backless Tee",
    "price": "4,99",
    "url": "https://eur.shein.com/SHEIN-SXY-Cold-Shoulder-Backless-Tee-p-3072500-cat-2223.html?scici=Search~~EditSearch~~1~~top~~~~0"
  },
  {
    "name": "SHEIN Mock-Neck Tied Backless Crop Top",
    "price": "4,99",
    "url": "https://eur.shein.com/SHEIN-Mock-Neck-Tied-Backless-Crop-Top-p-3221674-cat-1738.html?scici=Search~~EditSearch~~1~~top~~~~0"
  },
  {
    "name": "O-ring Linked Backless Crop Halter Top",
    "price": "5,00",
    "url": "https://eur.shein.com/O-ring-Linked-Backless-Crop-Halter-Top-p-3144867-cat-1779.html?scici=Search~~EditSearch~~1~~top~~~~0"
  },
  {
    "name": "SHEIN PETITE Solid Slim Cami Top",
    "price": "4,00",
    "url": "https://eur.shein.com/SHEIN-PETITE-Solid-Slim-Cami-Top-p-4389196-cat-1779.html?scici=Search~~EditSearch~~1~~top~~~~0"
  },
  {
    "name": "Mesh Insert Draped Collar Lace Up Back Cami Top",
    "price": "7,00",
    "url": "https://eur.shein.com/Mesh-Insert-Draped-Collar-Lace-Up-Back-Cami-Top-p-5954182-cat-1779.html?scici=Search~~EditSearch~~1~~top~~~~0"
  },
  {
    "name": "Marble Print Tie Front Crop Top",
    "price": "9,99",
    "url": "https://eur.shein.com/Marble-Print-Tie-Front-Crop-Top-p-3421950-cat-2223.html?scici=Search~~EditSearch~~1~~top~~~~0"
  },
  {
    "name": "SHEIN SXY Solid Rib-Knit Crop Tank Top",
    "price": "5,00",
    "url": "https://eur.shein.com/SHEIN-SXY-Solid-Rib-Knit-Crop-Tank-Top-p-3022084-cat-1779.html?scici=Search~~EditSearch~~1~~top~~~~0"
  },
  {
    "name": "SHEIN SXY Racing Car Graphic Tie Back Crop Top",
    "price": "3,99 4,99",
    "url": "https://eur.shein.com/SHEIN-SXY-Racing-Car-Graphic-Tie-Back-Crop-Top-p-2870759-cat-1738.html?scici=Search~~EditSearch~~1~~top~~~~0"
  },
  {
    "name": "Snakeskin Print Tie Hem V-Neck Top",
    "price": "11,00",
    "url": "https://eur.shein.com/Snakeskin-Print-Tie-Hem-V-Neck-Top-p-2893348-cat-2223.html?scici=Search~~EditSearch~~1~~top~~~~0"
  },
  {
    "name": "SHEIN Argyle Print Tank Top",
    "price": "4,00",
    "url": "https://eur.shein.com/SHEIN-Argyle-Print-Tank-Top-p-3159653-cat-1779.html?scici=Search~~EditSearch~~1~~top~~~~0"
  },
  {
    "name": "Lace Up Front Stitch Trim Halter Top",
    "price": "4,00",
    "url": "https://eur.shein.com/Lace-Up-Front-Stitch-Trim-Halter-Top-p-3025341-cat-1779.html?scici=Search~~EditSearch~~1~~top~~~~0"
  },
  {
    "name": "Solid Zip Front Tank Top",
    "price": "6,00",
    "url": "https://eur.shein.com/Solid-Zip-Front-Tank-Top-p-2232678-cat-1779.html?scici=Search~~EditSearch~~1~~top~~~~0"
  },
  {
    "name": "SHEIN Rib-knit Solid Crop Cami Top",
    "price": "4,00",
    "url": "https://eur.shein.com/SHEIN-Rib-knit-Solid-Crop-Cami-Top-p-2589046-cat-1779.html?scici=Search~~EditSearch~~1~~top~~~~0"
  },
  {
    "name": "SHEIN Lace Trim Tank Top",
    "price": "5,00",
    "url": "https://eur.shein.com/SHEIN-Lace-Trim-Tank-Top-p-2975317-cat-1779.html?scici=Search~~EditSearch~~1~~top~~~~0"
  },
  {
    "name": "Half Button Halter Top",
    "price": "8,00",
    "url": "https://eur.shein.com/Half-Button-Halter-Top-p-2985735-cat-1779.html?scici=Search~~EditSearch~~1~~top~~~~0"
  },
  {
    "name": "SHEIN Contrast Lace Panel Lettuce Edge Cami Top",
    "price": "2,99 4,00",
    "url": "https://eur.shein.com/SHEIN-Contrast-Lace-Panel-Lettuce-Edge-Cami-Top-p-1929134-cat-1779.html?scici=Search~~EditSearch~~1~~top~~~~0"
  },
  {
    "name": "Strap Detail Hanky Hem Lace Cami Top",
    "price": "5,49 7,00",
    "url": "https://eur.shein.com/Strap-Detail-Hanky-Hem-Lace-Cami-Top-p-2745057-cat-1779.html?scici=Search~~EditSearch~~1~~top~~~~0"
  },
  {
    "name": "SHEIN SXY Cut Out Solid Tank Top",
    "price": "4,00",
    "url": "https://eur.shein.com/SHEIN-SXY-Cut-Out-Solid-Tank-Top-p-2657762-cat-1779.html?scici=Search~~EditSearch~~1~~top~~~~0"
  },
  {
    "name": "SHEIN Ruched Sheer Mesh Crop Top",
    "price": "4,49 6,00",
    "url": "https://eur.shein.com/SHEIN-Ruched-Sheer-Mesh-Crop-Top-p-2685885-cat-2223.html?scici=Search~~EditSearch~~1~~top~~~~0"
  },
  {
    "name": "Tie Back Crop Cami Satin Top",
    "price": "5,00",
    "url": "https://eur.shein.com/Tie-Back-Crop-Cami-Satin-Top-p-2456487-cat-1779.html?scici=Search~~EditSearch~~1~~top~~~~0"
  },
  {
    "name": "SHEIN Lantern Sleeve Tie Back Top",
    "price": "9,00",
    "url": "https://eur.shein.com/SHEIN-Lantern-Sleeve-Tie-Back-Top-p-5142272-cat-2223.html?scici=Search~~EditSearch~~1~~top~~~~0"
  },
  {
    "name": "SHEIN V-neck Tied Open Back Crop Top",
    "price": "4,99",
    "url": "https://eur.shein.com/SHEIN-V-neck-Tied-Open-Back-Crop-Top-p-1414675-cat-1738.html?scici=Search~~EditSearch~~1~~top~~~~0"
  },
  {
    "name": "SHEIN Sweetheart Neck Tie Back Crop Top",
    "price": "9,00",
    "url": "https://eur.shein.com/SHEIN-Sweetheart-Neck-Tie-Back-Crop-Top-p-3001027-cat-2223.html?scici=Search~~EditSearch~~1~~top~~~~0"
  },
  {
    "name": "SHEIN Marble Print Crop Halter Top",
    "price": "6,00",
    "url": "https://eur.shein.com/SHEIN-Marble-Print-Crop-Halter-Top-p-2976225-cat-1779.html?scici=Search~~EditSearch~~1~~top~~~~0"
  },
  {
    "name": "Plunging Neck Wrap Cross Tie Back Crop Top",
    "price": "6,00",
    "url": "https://eur.shein.com/Plunging-Neck-Wrap-Cross-Tie-Back-Crop-Top-p-1986949-cat-2223.html?scici=Search~~EditSearch~~1~~top~~~~0"
  },
  {
    "name": "Half Zipper Crop Tank Top",
    "price": "10,00",
    "url": "https://eur.shein.com/Half-Zipper-Crop-Tank-Top-p-2843965-cat-1779.html?scici=Search~~EditSearch~~1~~top~~~~0"
  },
  {
    "name": "Bell Sleeve Self-Tie Crop Top",
    "price": "11,00",
    "url": "https://eur.shein.com/Bell-Sleeve-Self-Tie-Crop-Top-p-534736-cat-1733.html?scici=Search~~EditSearch~~1~~top~~~~0"
  },
  {
    "name": "Lace Trim Tie Front Cami Crop Top",
    "price": "5,00",
    "url": "https://eur.shein.com/Lace-Trim-Tie-Front-Cami-Crop-Top-p-2733887-cat-1779.html?scici=Search~~EditSearch~~1~~top~~~~0"
  },
  {
    "name": "Ditsy Floral Print Lettuce Trim Tank Top",
    "price": "6,00",
    "url": "https://eur.shein.com/Ditsy-Floral-Print-Lettuce-Trim-Tank-Top-p-2116201-cat-1779.html?scici=Search~~EditSearch~~1~~top~~~~0"
  },
  {
    "name": "SHEIN Jacquard Lace Trim Cami Top",
    "price": "4,49 6,00",
    "url": "https://eur.shein.com/SHEIN-Jacquard-Lace-Trim-Cami-Top-p-6217187-cat-1779.html?scici=Search~~EditSearch~~1~~top~~~~0"
  },
  {
    "name": "SHEIN Asymmetrical Hem Rib-knit Top",
    "price": "4,99",
    "url": "https://eur.shein.com/SHEIN-Asymmetrical-Hem-Rib-knit-Top-p-2358858-cat-1738.html?scici=Search~~EditSearch~~1~~top~~~~0"
  },
  {
    "name": "Dot Print Ring Linked Asymmetrical Hem Top",
    "price": "8,00",
    "url": "https://eur.shein.com/Dot-Print-Ring-Linked-Asymmetrical-Hem-Top-p-3488783-cat-2223.html?scici=Search~~EditSearch~~1~~top~~~~0"
  },
  {
    "name": "SHEIN Knot Front Rib-knit Bardot Top",
    "price": "5,99",
    "url": "https://eur.shein.com/SHEIN-Knot-Front-Rib-knit-Bardot-Top-p-3425460-cat-1738.html?scici=Search~~EditSearch~~1~~top~~~~0"
  },
  {
    "name": "Solid Ruched Bust Cami Top",
    "price": "8,00",
    "url": "https://eur.shein.com/Solid-Ruched-Bust-Cami-Top-p-2203092-cat-1779.html?scici=Search~~EditSearch~~1~~top~~~~0"
  },
  {
    "name": "Textured Knit Tank Top",
    "price": "6,00",
    "url": "https://eur.shein.com/Textured-Knit-Tank-Top-p-6566357-cat-1779.html?scici=Search~~EditSearch~~1~~top~~~~0"
  },
  {
    "name": "Chain Detail Crop Cami Top",
    "price": "6,00",
    "url": "https://eur.shein.com/Chain-Detail-Crop-Cami-Top-p-6915932-cat-1779.html?scici=Search~~EditSearch~~1~~top~~~~0"
  },
  {
    "name": "Criss Cross Tie Back Crop Top",
    "price": "7,00",
    "url": "https://eur.shein.com/Criss-Cross-Tie-Back-Crop-Top-p-3400681-cat-2223.html?scici=Search~~EditSearch~~1~~top~~~~0"
  },
  {
    "name": "SHEIN SXY Lace Up Backless Crop Tube Top",
    "price": "4,00",
    "url": "https://eur.shein.com/SHEIN-SXY-Lace-Up-Backless-Crop-Tube-Top-p-4538201-cat-2223.html?scici=Search~~EditSearch~~1~~top~~~~0"
  },
  {
    "name": "Mock Neck Knot Side Ruched Tank Top",
    "price": "6,00",
    "url": "https://eur.shein.com/Mock-Neck-Knot-Side-Ruched-Tank-Top-p-3459544-cat-1779.html?scici=Search~~EditSearch~~1~~top~~~~0"
  },
  {
    "name": "SHEIN Rib-knit Crop Tank Top",
    "price": "2,99 4,00",
    "url": "https://eur.shein.com/SHEIN-Rib-knit-Crop-Tank-Top-p-3040634-cat-1779.html?scici=Search~~EditSearch~~1~~top~~~~0"
  },
  {
    "name": "DAZY Angel & Tree Print Crop Tube Top",
    "price": "3,00",
    "url": "https://eur.shein.com/DAZY-Angel-Tree-Print-Crop-Tube-Top-p-6719882-cat-2223.html?scici=Search~~EditSearch~~1~~top~~~~0"
  },
  {
    "name": "Ruched Knot Back Crop Blouse",
    "price": "10,00",
    "url": "https://eur.shein.com/Ruched-Knot-Back-Crop-Blouse-p-4218031-cat-1733.html?scici=Search~~EditSearch~~1~~top~~~~0"
  },
  {
    "name": "SHEIN Rib-knit Cami Top",
    "price": "7,00",
    "url": "https://eur.shein.com/SHEIN-Rib-knit-Cami-Top-p-3506603-cat-1779.html?scici=Search~~EditSearch~~1~~top~~~~0"
  },
  {
    "name": "Rhinestone Heart Cut Out Front Crop Top",
    "price": "8,99",
    "url": "https://eur.shein.com/Rhinestone-Heart-Cut-Out-Front-Crop-Top-p-3407791-cat-1738.html?scici=Search~~EditSearch~~1~~top~~~~0"
  },
  {
    "name": "SHEIN Square Neck Crop Ribbed Knit Top",
    "price": "8,00",
    "url": "https://eur.shein.com/SHEIN-Square-Neck-Crop-Ribbed-Knit-Top-p-3073003-cat-2223.html?scici=Search~~EditSearch~~1~~top~~~~0"
  },
  {
    "name": "SHEIN SXY Open Back Halter Top",
    "price": "3,00",
    "url": "https://eur.shein.com/SHEIN-SXY-Open-Back-Halter-Top-p-3148327-cat-1779.html?scici=Search~~EditSearch~~1~~top~~~~0"
  },
  {
    "name": "Contrast Lace Ruched Bust Cami Top",
    "price": "4,49 6,00",
    "url": "https://eur.shein.com/Contrast-Lace-Ruched-Bust-Cami-Top-p-2694680-cat-1779.html?scici=Search~~EditSearch~~1~~top~~~~0"
  },
  {
    "name": "SHEIN Ruched Detail Crop Cami Top",
    "price": "5,00",
    "url": "https://eur.shein.com/SHEIN-Ruched-Detail-Crop-Cami-Top-p-2515900-cat-1779.html?scici=Search~~EditSearch~~1~~top~~~~0"
  },
  {
    "name": "Lace Cami Top",
    "price": "7,00",
    "url": "https://eur.shein.com/Lace-Cami-Top-p-2714481-cat-1779.html?scici=Search~~EditSearch~~1~~top~~~~0"
  },
  {
    "name": "SHEIN Lettuce Edge Ruched Bust Solid Top",
    "price": "4,99",
    "url": "https://eur.shein.com/SHEIN-Lettuce-Edge-Ruched-Bust-Solid-Top-p-1392392-cat-1738.html?scici=Search~~EditSearch~~1~~top~~~~0"
  },
  {
    "name": "Crisscross Tied Backless Rib Knit Top",
    "price": "5,00",
    "url": "https://eur.shein.com/Crisscross-Tied-Backless-Rib-Knit-Top-p-2551687-cat-1779.html?scici=Search~~EditSearch~~1~~top~~~~0"
  },
  {
    "name": "Tie Dye Triangle Halter Bikini Top",
    "price": "5,00",
    "url": "https://eur.shein.com/Tie-Dye-Triangle-Halter-Bikini-Top-p-1022078-cat-2291.html?scici=Search~~RecommendList~~RS_emarsys,RJ_NoFaultTolerant~~Recommendations%20For%20You~~SPcSearchResultRecommendationsForYou~~0"
  },
  {
    "name": "Ring Linked Bikini Top",
    "price": "6,00",
    "url": "https://eur.shein.com/Ring-Linked-Bikini-Top-p-1027860-cat-2291.html?scici=Search~~RecommendList~~RS_emarsys,RJ_NoFaultTolerant~~Recommendations%20For%20You~~SPcSearchResultRecommendationsForYou~~0"
  },
  {
    "name": "Tie Back Triangle Bikini Top",
    "price": "5,00",
    "url": "https://eur.shein.com/Tie-Back-Triangle-Bikini-Top-p-1051194-cat-2291.html?scici=Search~~RecommendList~~RS_emarsys,RJ_NoFaultTolerant~~Recommendations%20For%20You~~SPcSearchResultRecommendationsForYou~~0"
  },
  {
    "name": "SHEIN Lace Trim Hook and Eye Front Bustier Cami Top",
    "price": "5,49 7,00",
    "url": "https://eur.shein.com/Lace-Trim-Hook-and-Eye-Front-Bustier-Cami-Top-p-1054047-cat-1779.html?scici=Search~~RecommendList~~RS_emarsys,RJ_NoFaultTolerant~~Recommendations%20For%20You~~SPcSearchResultRecommendationsForYou~~0"
  },
  {
    "name": "SHEIN Lettuce Trim Butterfly Embroidery Crop Top",
    "price": "5,99",
    "url": "https://eur.shein.com/Lettuce-Trim-Butterfly-Embroidery-Crop-Top-p-1056173-cat-1738.html?scici=Search~~RecommendList~~RS_emarsys,RJ_NoFaultTolerant~~Recommendations%20For%20You~~SPcSearchResultRecommendationsForYou~~0"
  },
  {
    "name": "",
    "price": "",
    "url": "https://eur.shein.com/Frill-Trim-Shirred-Tube-Top-p-1075984-cat-2223.html?scici=Search~~RecommendList~~RS_emarsys,RJ_NoFaultTolerant~~Recommendations%20For%20You~~SPcSearchResultRecommendationsForYou~~0"
  },
  {
    "name": "",
    "price": "",
    "url": "https://eur.shein.com/Crop-Criss-Cross-Halter-Top-p-1095835-cat-1779.html?scici=Search~~RecommendList~~RS_emarsys,RJ_NoFaultTolerant~~Recommendations%20For%20You~~SPcSearchResultRecommendationsForYou~~0"
  },
  {
    "name": "",
    "price": "",
    "url": "https://eur.shein.com/Lace-Up-Backless-Solid-Cami-Top-p-1107921-cat-1779.html?scici=Search~~RecommendList~~RS_emarsys,RJ_NoFaultTolerant~~Recommendations%20For%20You~~SPcSearchResultRecommendationsForYou~~0"
  },
  {
    "name": "",
    "price": "",
    "url": "https://eur.shein.com/Tied-Open-Back-Crop-Halter-Top-p-1113766-cat-1779.html?scici=Search~~RecommendList~~RS_emarsys,RJ_NoFaultTolerant~~Recommendations%20For%20You~~SPcSearchResultRecommendationsForYou~~0"
  },
  {
    "name": "",
    "price": "",
    "url": "https://eur.shein.com/Solid-Crisscross-Self-Tie-Crop-Top-p-1125193-cat-2223.html?scici=Search~~RecommendList~~RS_emarsys,RJ_NoFaultTolerant~~Recommendations%20For%20You~~SPcSearchResultRecommendationsForYou~~0"
  },
  {
    "name": "",
    "price": "",
    "url": "https://eur.shein.com/Drawstring-Front-Bikini-Top-p-1151505-cat-2291.html?scici=Search~~RecommendList~~RS_emarsys,RJ_NoFaultTolerant~~Recommendations%20For%20You~~SPcSearchResultRecommendationsForYou~~0"
  },
  {
    "name": "",
    "price": "",
    "url": "https://eur.shein.com/One-Shoulder-Rib-knit-Crop-Top-p-1179502-cat-2223.html?scici=Search~~RecommendList~~RS_emarsys,RJ_NoFaultTolerant~~Recommendations%20For%20You~~SPcSearchResultRecommendationsForYou~~0"
  },
  {
    "name": "",
    "price": "",
    "url": "https://eur.shein.com/V-Neck-Bikini-Top-p-1224571-cat-2291.html?scici=Search~~RecommendList~~RS_emarsys,RJ_NoFaultTolerant~~Recommendations%20For%20You~~SPcSearchResultRecommendationsForYou~~0"
  },
  {
    "name": "",
    "price": "",
    "url": "https://eur.shein.com/Ditsy-Floral-Crop-Cami-Top-p-1255652-cat-1779.html?scici=Search~~RecommendList~~RS_emarsys,RJ_NoFaultTolerant~~Recommendations%20For%20You~~SPcSearchResultRecommendationsForYou~~0"
  },
  {
    "name": "",
    "price": "",
    "url": "https://eur.shein.com/Girls-Ribbed-Butterfly-Graphic-Cropped-Cami-Top-p-1259509-cat-2830.html?scici=Search~~RecommendList~~RS_emarsys,RJ_NoFaultTolerant~~Recommendations%20For%20You~~SPcSearchResultRecommendationsForYou~~0"
  },
  {
    "name": "",
    "price": "",
    "url": "https://eur.shein.com/Ditsy-Floral-Self-Tie-Surplice-Wrap-Top-p-1263954-cat-1733.html?scici=Search~~RecommendList~~RS_emarsys,RJ_NoFaultTolerant~~Recommendations%20For%20You~~SPcSearchResultRecommendationsForYou~~0"
  },
  {
    "name": "",
    "price": "",
    "url": "https://eur.shein.com/Contrast-Neck-Rainbow-Striped-Top-p-1269973-cat-1738.html?scici=Search~~RecommendList~~RS_emarsys,RJ_NoFaultTolerant~~Recommendations%20For%20You~~SPcSearchResultRecommendationsForYou~~0"
  },
  {
    "name": "",
    "price": "",
    "url": "https://eur.shein.com/Dalmatian-Cut-out-One-Shoulder-Bikini-Top-p-1276425-cat-2291.html?scici=Search~~RecommendList~~RS_emarsys,RJ_NoFaultTolerant~~Recommendations%20For%20You~~SPcSearchResultRecommendationsForYou~~0"
  },
  {
    "name": "",
    "price": "",
    "url": "https://eur.shein.com/Tie-Dye-Lace-Up-Back-Cami-Top-p-1287181-cat-1779.html?scici=Search~~RecommendList~~RS_emarsys,RJ_NoFaultTolerant~~Recommendations%20For%20You~~SPcSearchResultRecommendationsForYou~~0"
  },
  {
    "name": "",
    "price": "",
    "url": "https://eur.shein.com/Letter-Graphic-Crop-Cami-Top-p-1309778-cat-1779.html?scici=Search~~RecommendList~~RS_emarsys,RJ_NoFaultTolerant~~Recommendations%20For%20You~~SPcSearchResultRecommendationsForYou~~0"
  },
  {
    "name": "",
    "price": "",
    "url": "https://eur.shein.com/Button-Half-Placket-Rib-knit-Tank-Top-p-1344153-cat-1779.html?scici=Search~~RecommendList~~RS_emarsys,RJ_NoFaultTolerant~~Recommendations%20For%20You~~SPcSearchResultRecommendationsForYou~~0"
  },
  {
    "name": "",
    "price": "",
    "url": "https://eur.shein.com/Contrast-Striped-Letter-Graphic-Top-p-1347625-cat-1733.html?scici=Search~~RecommendList~~RS_emarsys,RJ_NoFaultTolerant~~Recommendations%20For%20You~~SPcSearchResultRecommendationsForYou~~0"
  },
  {
    "name": "",
    "price": "",
    "url": "https://eur.shein.com/Button-Front-Crop-Top-p-1351151-cat-1738.html?scici=Search~~RecommendList~~RS_emarsys,RJ_NoFaultTolerant~~Recommendations%20For%20You~~SPcSearchResultRecommendationsForYou~~0"
  },
  {
    "name": "",
    "price": "",
    "url": "https://eur.shein.com/Notch-Neck-Lettuce-Edge-Rib-knit-Tank-Top-p-1353755-cat-1779.html?scici=Search~~RecommendList~~RS_emarsys,RJ_NoFaultTolerant~~Recommendations%20For%20You~~SPcSearchResultRecommendationsForYou~~0"
  },
  {
    "name": "",
    "price": "",
    "url": "https://eur.shein.com/Crop-Cami-Top-p-1364455-cat-1779.html?scici=Search~~RecommendList~~RS_emarsys,RJ_NoFaultTolerant~~Recommendations%20For%20You~~SPcSearchResultRecommendationsForYou~~0"
  },
  {
    "name": "SHEIN Cowl Neck Open-Back Cropped Halter Top",
    "price": "5,00",
    "url": "https://eur.shein.com/SHEIN-Cowl-Neck-Open-Back-Cropped-Halter-Top-p-2125808-cat-1779.html?scici=Search~~EditSearch~~1~~top~~~~0"
  },
  {
    "name": "SHEIN Twist Front Tube Top",
    "price": "3,00 4,00",
    "url": "https://eur.shein.com/SHEIN-Twist-Front-Tube-Top-p-2676963-cat-2223.html?scici=Search~~EditSearch~~1~~top~~~~0"
  },
  {
    "name": "Striped Tie Back Crop Halter Top",
    "price": "6,00",
    "url": "https://eur.shein.com/Striped-Tie-Back-Crop-Halter-Top-p-2701297-cat-1779.html?scici=Search~~EditSearch~~1~~top~~~~0"
  },
  {
    "name": "SHEIN V-Neck Rib-knit Top",
    "price": "4,99",
    "url": "https://eur.shein.com/SHEIN-V-Neck-Rib-knit-Top-p-2038589-cat-1738.html?scici=Search~~EditSearch~~1~~top~~~~0"
  },
  {
    "name": "SHEIN Ribbed Drop Shoulder Crop Top",
    "price": "4,99",
    "url": "https://eur.shein.com/SHEIN-Ribbed-Drop-Shoulder-Crop-Top-p-1511718-cat-1738.html?scici=Search~~EditSearch~~1~~top~~~~0"
  },
  {
    "name": "Lace Up Front Shirred Cami Top",
    "price": "10,00",
    "url": "https://eur.shein.com/Lace-Up-Front-Shirred-Cami-Top-p-1741661-cat-1779.html?scici=Search~~EditSearch~~1~~top~~~~0"
  },
  {
    "name": "SHEIN BASICS V-Neck Crop Top",
    "price": "9,99",
    "url": "https://eur.shein.com/SHEIN-BASICS-V-Neck-Crop-Top-p-1538551-cat-1738.html?scici=Search~~EditSearch~~1~~top~~~~0"
  },
  {
    "name": "SHEIN Slogan Graphic Form Fitted Crop Top",
    "price": "4,99",
    "url": "https://eur.shein.com/SHEIN-Slogan-Graphic-Form-Fitted-Crop-Top-p-1166523-cat-1738.html?scici=Search~~EditSearch~~1~~top~~~~0"
  },
  {
    "name": "Lantern Sleeve Shirred Back Crop Top",
    "price": "11,00",
    "url": "https://eur.shein.com/Lantern-Sleeve-Shirred-Back-Crop-Top-p-6808432-cat-1733.html?scici=Search~~EditSearch~~1~~top~~~~0"
  },
  {
    "name": "Ditsy Floral Frill Trim Crop Blouse",
    "price": "9,00",
    "url": "https://eur.shein.com/Ditsy-Floral-Frill-Trim-Crop-Blouse-p-2278040-cat-1733.html?scici=Search~~EditSearch~~1~~top~~~~0"
  },
  {
    "name": "Cut Out Front Pearl Detail Crop Top",
    "price": "12,99",
    "url": "https://eur.shein.com/Cut-Out-Front-Pearl-Detail-Crop-Top-p-3137080-cat-2223.html?scici=Search~~EditSearch~~1~~top~~~~0"
  },
  {
    "name": "SHEIN Allover Print Tank Crop Top",
    "price": "7,00",
    "url": "https://eur.shein.com/SHEIN-Allover-Print-Tank-Crop-Top-p-3281818-cat-1779.html?scici=Search~~EditSearch~~1~~top~~~~0"
  },
  {
    "name": "SHEIN Ditsy Floral Print Lace Trim Cami Top",
    "price": "4,00",
    "url": "https://eur.shein.com/SHEIN-Ditsy-Floral-Print-Lace-Trim-Cami-Top-p-8093777-cat-1779.html?scici=Search~~EditSearch~~1~~top~~~~0"
  },
  {
    "name": "Color Block Top-stitching Ribbed Knit Crop Top",
    "price": "7,49 9,99",
    "url": "https://eur.shein.com/Color-Block-Top-stitching-Ribbed-Knit-Crop-Top-p-6729502-cat-1738.html?scici=Search~~EditSearch~~1~~top~~~~0"
  },
  {
    "name": "SHEIN Lace Trim Tank Top",
    "price": "5,00",
    "url": "https://eur.shein.com/SHEIN-Lace-Trim-Tank-Top-p-3371737-cat-1779.html?scici=Search~~EditSearch~~1~~top~~~~0"
  },
  {
    "name": "Plain Drawstring Shirred Tank Top",
    "price": "5,00",
    "url": "https://eur.shein.com/Plain-Drawstring-Shirred-Tank-Top-p-3146496-cat-1779.html?scici=Search~~EditSearch~~1~~top~~~~0"
  },
  {
    "name": "Floral Embroidery Sheer Mesh Top",
    "price": "7,00",
    "url": "https://eur.shein.com/Floral-Embroidery-Sheer-Mesh-Top-p-2627334-cat-2223.html?scici=Search~~EditSearch~~1~~top~~~~0"
  },
  {
    "name": "Satin Tie Back Backless Halter Top",
    "price": "7,00",
    "url": "https://eur.shein.com/Satin-Tie-Back-Backless-Halter-Top-p-3166447-cat-1779.html?scici=Search~~EditSearch~~1~~top~~~~0"
  },
  {
    "name": "Tie Front Lace Top Without Camisole",
    "price": "5,49 7,00",
    "url": "https://eur.shein.com/Tie-Front-Lace-Top-Without-Camisole-p-2489046-cat-2223.html?scici=Search~~EditSearch~~1~~top~~~~0"
  },
  {
    "name": "SHEIN Lettuce Trim Colorblock Halter Top",
    "price": "3,00",
    "url": "https://eur.shein.com/SHEIN-Lettuce-Trim-Colorblock-Halter-Top-p-2434374-cat-1779.html?scici=Search~~EditSearch~~1~~top~~~~0"
  },
  {
    "name": "SHEIN Floral Print Crop Cami Top",
    "price": "8,00",
    "url": "https://eur.shein.com/SHEIN-Floral-Print-Crop-Cami-Top-p-6577157-cat-1779.html?scici=Search~~EditSearch~~1~~top~~~~0"
  },
  {
    "name": "Surplice Neck Crisscross Tie Back Rib Knit Crop Top",
    "price": "8,00 9,00",
    "url": "https://eur.shein.com/Surplice-Neck-Crisscross-Tie-Back-Rib-Knit-Crop-Top-p-6248722-cat-2223.html?scici=Search~~EditSearch~~1~~top~~~~0"
  },
  {
    "name": "SHEIN Form-Fitting Mock Neck Crop Top",
    "price": "3,99",
    "url": "https://eur.shein.com/SHEIN-Form-Fitting-Mock-Neck-Crop-Top-p-5142487-cat-1738.html?scici=Search~~EditSearch~~1~~top~~~~0"
  },
  {
    "name": "High Neck Cut Out Front Crop Top",
    "price": "14,99",
    "url": "https://eur.shein.com/High-Neck-Cut-Out-Front-Crop-Top-p-6806872-cat-1738.html?scici=Search~~EditSearch~~1~~top~~~~0"
  },
  {
    "name": "Ring Linked Tie Back Crop Top",
    "price": "7,00",
    "url": "https://eur.shein.com/Ring-Linked-Tie-Back-Crop-Top-p-7081782-cat-2223.html?scici=Search~~EditSearch~~1~~top~~~~0"
  },
  {
    "name": "SHEIN PETITE Square Neck Lantern Sleeve Top",
    "price": "4,99",
    "url": "https://eur.shein.com/SHEIN-PETITE-Square-Neck-Lantern-Sleeve-Top-p-7455037-cat-1738.html?scici=Search~~EditSearch~~1~~top~~~~0"
  },
  {
    "name": "Patched Pocket Twist Front Crop Blouse",
    "price": "11,00",
    "url": "https://eur.shein.com/Patched-Pocket-Twist-Front-Crop-Blouse-p-6920907-cat-1733.html?scici=Search~~EditSearch~~1~~top~~~~0"
  },
  {
    "name": "Asymmetrical Neck Ribbed Knit Crop Top",
    "price": "4,00",
    "url": "https://eur.shein.com/Asymmetrical-Neck-Ribbed-Knit-Crop-Top-p-6206097-cat-2223.html?scici=Search~~EditSearch~~1~~top~~~~0"
  },
  {
    "name": "SHEIN Solid Textured Tank Top",
    "price": "5,00",
    "url": "https://eur.shein.com/SHEIN-Solid-Textured-Tank-Top-p-5313552-cat-1779.html?scici=Search~~EditSearch~~1~~top~~~~0"
  },
  {
    "name": "SHEIN Floral Mesh Lettuce Trim Top",
    "price": "5,00",
    "url": "https://eur.shein.com/SHEIN-Floral-Mesh-Lettuce-Trim-Top-p-5591067-cat-2223.html?scici=Search~~EditSearch~~1~~top~~~~0"
  },
  {
    "name": "ROMWE X Goldendazeillustration Floral Print Shirred Flounce Sleeve Blouse",
    "price": "9,00",
    "url": "https://eur.shein.com/ROMWE-X-Goldendazeillustration-Floral-Print-Shirred-Flounce-Sleeve-Blouse-p-5485502-cat-1733.html?scici=Search~~EditSearch~~1~~top~~~~0"
  },
  {
    "name": "Floral Print Sweetheart Neck Lantern Sleeve Crop Blouse",
    "price": "10,00",
    "url": "https://eur.shein.com/Floral-Print-Sweetheart-Neck-Lantern-Sleeve-Crop-Blouse-p-5201772-cat-1733.html?scici=Search~~EditSearch~~1~~top~~~~0"
  },
  {
    "name": "Solid Rib Knit Tank Top",
    "price": "5,00",
    "url": "https://eur.shein.com/Solid-Rib-Knit-Tank-Top-p-3313192-cat-1779.html?scici=Search~~EditSearch~~1~~top~~~~0"
  },
  {
    "name": "Contrast Lace Hem Cami Top",
    "price": "6,00",
    "url": "https://eur.shein.com/Contrast-Lace-Hem-Cami-Top-p-2986582-cat-1779.html?scici=Search~~EditSearch~~1~~top~~~~0"
  },
  {
    "name": "SHEIN SXY Lace Up Back Crop Cami Top",
    "price": "4,00",
    "url": "https://eur.shein.com/SHEIN-SXY-Lace-Up-Back-Crop-Cami-Top-p-2893549-cat-1779.html?scici=Search~~EditSearch~~1~~top~~~~0"
  },
  {
    "name": "Low Back Ring Detail Halter Top",
    "price": "5,00",
    "url": "https://eur.shein.com/Low-Back-Ring-Detail-Halter-Top-p-2513824-cat-1779.html?scici=Search~~EditSearch~~1~~top~~~~0"
  },
  {
    "name": "Drawstring Ruched Side Bustier Cami Top",
    "price": "7,00",
    "url": "https://eur.shein.com/Drawstring-Ruched-Side-Bustier-Cami-Top-p-3278862-cat-1779.html?scici=Search~~EditSearch~~1~~top~~~~0"
  },
  {
    "name": "Paisley Print Hanky Hem Cami Top",
    "price": "5,00",
    "url": "https://eur.shein.com/Paisley-Print-Hanky-Hem-Cami-Top-p-3062135-cat-1779.html?scici=Search~~EditSearch~~1~~top~~~~0"
  },
  {
    "name": "SHEIN Button Up Rib-knit Crop Top",
    "price": "4,99",
    "url": "https://eur.shein.com/SHEIN-Button-Up-Rib-knit-Crop-Top-p-3034256-cat-1738.html?scici=Search~~EditSearch~~1~~top~~~~0"
  },
  {
    "name": "Drawstring Front Asymmetrical Hem Halter Top",
    "price": "5,00",
    "url": "https://eur.shein.com/Drawstring-Front-Asymmetrical-Hem-Halter-Top-p-2412888-cat-1779.html?scici=Search~~EditSearch~~1~~top~~~~0"
  },
  {
    "name": "SHEIN Lace Crop Cami Top",
    "price": "6,00",
    "url": "https://eur.shein.com/SHEIN-Lace-Crop-Cami-Top-p-2665893-cat-1779.html?scici=Search~~EditSearch~~1~~top~~~~0"
  },
  {
    "name": "SHEIN Honey Graphic Tie Dye Top",
    "price": "4,99",
    "url": "https://eur.shein.com/SHEIN-Honey-Graphic-Tie-Dye-Top-p-2544644-cat-1738.html?scici=Search~~EditSearch~~1~~top~~~~0"
  },
  {
    "name": "Contrast Lace Cami Top",
    "price": "5,49 7,00",
    "url": "https://eur.shein.com/Contrast-Lace-Cami-Top-p-2353899-cat-1779.html?scici=Search~~EditSearch~~1~~top~~~~0"
  },
  {
    "name": "Butterfly Print Crop Cami Top",
    "price": "2,99 4,00",
    "url": "https://eur.shein.com/Butterfly-Print-Crop-Cami-Top-p-2320361-cat-1779.html?scici=Search~~EditSearch~~1~~top~~~~0"
  },
  {
    "name": "SHEIN Square Neck Ruched Bust Crop Top",
    "price": "5,99",
    "url": "https://eur.shein.com/SHEIN-Square-Neck-Ruched-Bust-Crop-Top-p-1520966-cat-1738.html?scici=Search~~EditSearch~~1~~top~~~~0"
  },
  {
    "name": "Graphic Print Tank Top",
    "price": "5,00",
    "url": "https://eur.shein.com/Graphic-Print-Tank-Top-p-3166389-cat-1779.html?scici=Search~~EditSearch~~1~~top~~~~0"
  },
  {
    "name": "Cutout Cropped Cami Top",
    "price": "5,00",
    "url": "https://eur.shein.com/Cutout-Cropped-Cami-Top-p-789788-cat-1779.html?scici=Search~~EditSearch~~1~~top~~~~0"
  },
  {
    "name": "Solid Dual Strap Shoulder Cami Top",
    "price": "5,00",
    "url": "https://eur.shein.com/Solid-Dual-Strap-Shoulder-Cami-Top-p-2828614-cat-1779.html?scici=Search~~EditSearch~~1~~top~~~~0"
  },
  {
    "name": "SHEIN Frilled Strap Tie Front Ruched Bust Crop Top",
    "price": "5,00",
    "url": "https://eur.shein.com/SHEIN-Frilled-Strap-Tie-Front-Ruched-Bust-Crop-Top-p-1269851-cat-1779.html?scici=Search~~EditSearch~~1~~top~~~~0"
  },
  {
    "name": "Lace Trim Open Front Top & Cami Top",
    "price": "12,00",
    "url": "https://eur.shein.com/Lace-Trim-Open-Front-Top-Cami-Top-p-7861927-cat-1780.html?scici=Search~~EditSearch~~1~~top~~~~0"
  },
  {
    "name": "SHEIN V Neck Ribbed Crop Top",
    "price": "4,99",
    "url": "https://eur.shein.com/SHEIN-V-Neck-Ribbed-Crop-Top-p-1613355-cat-1738.html?scici=Search~~EditSearch~~1~~top~~~~0"
  },
  {
    "name": "SHEIN BASICS Solid Fitted Crop Top",
    "price": "7,99",
    "url": "https://eur.shein.com/SHEIN-BASICS-Solid-Fitted-Crop-Top-p-1536447-cat-1738.html?scici=Search~~EditSearch~~1~~top~~~~0"
  },
  {
    "name": "SHEIN SXY Cutout Rib Knit Tank Top",
    "price": "5,00",
    "url": "https://eur.shein.com/SHEIN-SXY-Cutout-Rib-Knit-Tank-Top-p-3039564-cat-1779.html?scici=Search~~EditSearch~~1~~top~~~~0"
  },
  {
    "name": "SHEIN Plants Print Lace Up Front Tank Top",
    "price": "8,00",
    "url": "https://eur.shein.com/SHEIN-Plants-Print-Lace-Up-Front-Tank-Top-p-7646457-cat-1779.html?scici=Search~~EditSearch~~1~~top~~~~0"
  },
  {
    "name": "SHEIN Solid Self-Tie Back Long Sleeve Crop Top",
    "price": "4,99",
    "url": "https://eur.shein.com/SHEIN-Solid-Self-Tie-Back-Long-Sleeve-Crop-Top-p-1449861-cat-1738.html?scici=Search~~EditSearch~~1~~top~~~~0"
  },
  {
    "name": "SHEIN PETITE Garment Eyelet Chain Front Abstract Print Top",
    "price": "9,99",
    "url": "https://eur.shein.com/SHEIN-PETITE-Garment-Eyelet-Chain-Front-Abstract-Print-Top-p-7228432-cat-1738.html?scici=Search~~EditSearch~~1~~top~~~~0"
  },
  {
    "name": "Contrast Lace Criss Cross Halter Top",
    "price": "10,00",
    "url": "https://eur.shein.com/Contrast-Lace-Criss-Cross-Halter-Top-p-2687126-cat-1779.html?scici=Search~~EditSearch~~1~~top~~~~0"
  },
  {
    "name": "SHEIN Cut Out Crop Tank Top",
    "price": "4,00",
    "url": "https://eur.shein.com/SHEIN-Cut-Out-Crop-Tank-Top-p-5750492-cat-1779.html?scici=Search~~EditSearch~~1~~top~~~~0"
  },
  {
    "name": "Solid Cut Out Back Tank Top",
    "price": "6,00",
    "url": "https://eur.shein.com/Solid-Cut-Out-Back-Tank-Top-p-2312880-cat-1779.html?scici=Search~~EditSearch~~1~~top~~~~0"
  },
  {
    "name": "Allover Print Petal Sleeve Blouse",
    "price": "11,00",
    "url": "https://eur.shein.com/Allover-Print-Petal-Sleeve-Blouse-p-7565832-cat-1733.html?scici=Search~~EditSearch~~1~~top~~~~0"
  },
  {
    "name": "SHEIN Tie Front Ruched Bust Textured Mesh Crop Top",
    "price": "7,99",
    "url": "https://eur.shein.com/SHEIN-Tie-Front-Ruched-Bust-Textured-Mesh-Crop-Top-p-2168952-cat-2223.html?scici=Search~~EditSearch~~1~~top~~~~0"
  },
  {
    "name": "SHEIN Solid Lace Trim Cami Top",
    "price": "4,00",
    "url": "https://eur.shein.com/SHEIN-Solid-Lace-Trim-Cami-Top-p-4329986-cat-1779.html?scici=Search~~EditSearch~~1~~top~~~~0"
  },
  {
    "name": "SHEIN NEWNESS Frill Strap Jacquard Cami Top",
    "price": "9,00",
    "url": "https://eur.shein.com/SHEIN-NEWNESS-Frill-Strap-Jacquard-Cami-Top-p-4096326-cat-1779.html?scici=Search~~EditSearch~~1~~top~~~~0"
  },
  {
    "name": "SHEIN 3pcs Lace Detail Lettuce Trim Cami Top & Tank Top",
    "price": "9,99 13,00",
    "url": "https://eur.shein.com/SHEIN-3pcs-Lace-Detail-Lettuce-Trim-Cami-Top-Tank-Top-p-3469759-cat-1779.html?scici=Search~~EditSearch~~1~~top~~~~0"
  },
  {
    "name": "Stitch Trim Rib-knit Colorblock Tank Top",
    "price": "6,00",
    "url": "https://eur.shein.com/Stitch-Trim-Rib-knit-Colorblock-Tank-Top-p-2451265-cat-1779.html?scici=Search~~EditSearch~~1~~top~~~~0"
  },
  {
    "name": "Color-block Seam Front Crop Top",
    "price": "4,49 5,99",
    "url": "https://eur.shein.com/Color-block-Seam-Front-Crop-Top-p-4375616-cat-1738.html?scici=Search~~EditSearch~~1~~top~~~~0"
  },
  {
    "name": "SHEIN Crisscross Back Cami Top",
    "price": "3,00",
    "url": "https://eur.shein.com/SHEIN-Crisscross-Back-Cami-Top-p-6589747-cat-1779.html?scici=Search~~EditSearch~~1~~top~~~~0"
  },
  {
    "name": "SHEIN Figure Graphic Crop Tank Top",
    "price": "3,49 5,00",
    "url": "https://eur.shein.com/SHEIN-Figure-Graphic-Crop-Tank-Top-p-4778817-cat-1779.html?scici=Search~~EditSearch~~1~~top~~~~0"
  },
  {
    "name": "SHEIN Floral Print Round Neck Tank Top",
    "price": "4,00",
    "url": "https://eur.shein.com/SHEIN-Floral-Print-Round-Neck-Tank-Top-p-6296057-cat-1779.html?scici=Search~~EditSearch~~1~~top~~~~0"
  },
  {
    "name": "Ruched Bust Contrast Lace V-neck Top",
    "price": "5,99",
    "url": "https://eur.shein.com/Ruched-Bust-Contrast-Lace-V-neck-Top-p-6060042-cat-1738.html?scici=Search~~EditSearch~~1~~top~~~~0"
  },
  {
    "name": "Solid Slim Cami Crop Top",
    "price": "3,00",
    "url": "https://eur.shein.com/Solid-Slim-Cami-Crop-Top-p-4943402-cat-1779.html?scici=Search~~EditSearch~~1~~top~~~~0"
  },
  {
    "name": "SHEIN SXY Ruched Button Placket Solid Top",
    "price": "13,00",
    "url": "https://eur.shein.com/SHEIN-SXY-Ruched-Button-Placket-Solid-Top-p-4217481-cat-1738.html?scici=Search~~EditSearch~~1~~top~~~~0"
  },
  {
    "name": "Embroidery Mesh Scallop Trim Tie Back Blouse",
    "price": "9,00",
    "url": "https://eur.shein.com/Embroidery-Mesh-Scallop-Trim-Tie-Back-Blouse-p-6205932-cat-1733.html?scici=Search~~EditSearch~~1~~top~~~~0"
  },
  {
    "name": "Sun And Moon Print Crop Tank Top",
    "price": "4,00",
    "url": "https://eur.shein.com/Sun-And-Moon-Print-Crop-Tank-Top-p-5940897-cat-1779.html?scici=Search~~EditSearch~~1~~top~~~~0"
  },
  {
    "name": "Frill Trim Bell Sleeve Ruched Bust Milkmaid Top",
    "price": "9,49 12,00",
    "url": "https://eur.shein.com/Frill-Trim-Bell-Sleeve-Ruched-Bust-Milkmaid-Top-p-3774021-cat-1733.html?scici=Search~~EditSearch~~1~~top~~~~0"
  },
  {
    "name": "Sheer Mesh Cutout Tied Backless Top",
    "price": "10,00",
    "url": "https://eur.shein.com/Sheer-Mesh-Cutout-Tied-Backless-Top-p-3243176-cat-1779.html?scici=Search~~EditSearch~~1~~top~~~~0"
  },
  {
    "name": "SHEIN Crisscross Tied Crop Tube Top",
    "price": "4,00",
    "url": "https://eur.shein.com/SHEIN-Crisscross-Tied-Crop-Tube-Top-p-3034591-cat-2223.html?scici=Search~~EditSearch~~1~~top~~~~0"
  },
  {
    "name": "Solid Ruched Bust Scoop Neck Shirred Blouse",
    "price": "7,00",
    "url": "https://eur.shein.com/Solid-Ruched-Bust-Scoop-Neck-Shirred-Blouse-p-3005996-cat-1733.html?scici=Search~~EditSearch~~1~~top~~~~0"
  },
  {
    "name": "SHEIN NEWNESS Tie Front Lettuce Trim Mesh Top",
    "price": "8,00",
    "url": "https://eur.shein.com/SHEIN-NEWNESS-Tie-Front-Lettuce-Trim-Mesh-Top-p-3270494-cat-2223.html?scici=Search~~EditSearch~~1~~top~~~~0"
  },
  {
    "name": "Lace Trim Button Front Rib Knit Crop Top",
    "price": "5,00 8,00",
    "url": "https://eur.shein.com/Lace-Trim-Button-Front-Rib-Knit-Crop-Top-p-3167986-cat-2223.html?scici=Search~~EditSearch~~1~~top~~~~0"
  },
  {
    "name": "Satin Shirred Back Halter Top",
    "price": "5,00 6,00",
    "url": "https://eur.shein.com/Satin-Shirred-Back-Halter-Top-p-2691868-cat-1779.html?scici=Search~~EditSearch~~1~~top~~~~0"
  },
  {
    "name": "Contrast Lace Ruffle Hem Cami Top",
    "price": "7,00",
    "url": "https://eur.shein.com/Contrast-Lace-Ruffle-Hem-Cami-Top-p-8276077-cat-1779.html?scici=Search~~EditSearch~~1~~top~~~~0"
  },
  {
    "name": "SHEIN Mock Neck Letter Graphic Crop Top",
    "price": "4,49 4,99",
    "url": "https://eur.shein.com/SHEIN-Mock-Neck-Letter-Graphic-Crop-Top-p-3001412-cat-1738.html?scici=Search~~EditSearch~~1~~top~~~~0"
  },
  {
    "name": "SHEIN Butterfly Sleeve Waffle Knit Peplum Top",
    "price": "4,99",
    "url": "https://eur.shein.com/SHEIN-Butterfly-Sleeve-Waffle-Knit-Peplum-Top-p-3201931-cat-1738.html?scici=Search~~EditSearch~~1~~top~~~~0"
  },
  {
    "name": "Guipure Lace Panel Solid Blouse",
    "price": "11,00",
    "url": "https://eur.shein.com/Guipure-Lace-Panel-Solid-Blouse-p-3058678-cat-1733.html?scici=Search~~EditSearch~~1~~top~~~~0"
  },
  {
    "name": "Tie Back Surplice Front Blouse",
    "price": "8,00",
    "url": "https://eur.shein.com/Tie-Back-Surplice-Front-Blouse-p-2165965-cat-1733.html?scici=Search~~EditSearch~~1~~top~~~~0"
  },
  {
    "name": "Overlap Collar Tie Side Blouson Sleeve Blouse",
    "price": "10,00",
    "url": "https://eur.shein.com/Overlap-Collar-Tie-Side-Blouson-Sleeve-Blouse-p-2753149-cat-1733.html?scici=Search~~EditSearch~~1~~top~~~~0"
  },
  {
    "name": "SHEIN Ruched Drawstring Ditsy Floral Top",
    "price": "3,99",
    "url": "https://eur.shein.com/SHEIN-Ruched-Drawstring-Ditsy-Floral-Top-p-3001238-cat-1738.html?scici=Search~~EditSearch~~1~~top~~~~0"
  },
  {
    "name": "SHEIN SXY Solid Crop Tank Top",
    "price": "4,00",
    "url": "https://eur.shein.com/SHEIN-SXY-Solid-Crop-Tank-Top-p-2707502-cat-1779.html?scici=Search~~EditSearch~~1~~top~~~~0"
  },
  {
    "name": "Sweetheart Neck Ditsy Floral Shirred Blouse",
    "price": "14,00",
    "url": "https://eur.shein.com/Sweetheart-Neck-Ditsy-Floral-Shirred-Blouse-p-2971628-cat-1733.html?scici=Search~~EditSearch~~1~~top~~~~0"
  },
  {
    "name": "SHEIN SXY Crisscross Front Halter Top",
    "price": "10,00",
    "url": "https://eur.shein.com/SHEIN-SXY-Crisscross-Front-Halter-Top-p-2745056-cat-1779.html?scici=Search~~EditSearch~~1~~top~~~~0"
  },
  {
    "name": "Drawstring Front Backless Halter Top",
    "price": "4,00",
    "url": "https://eur.shein.com/Drawstring-Front-Backless-Halter-Top-p-2614421-cat-1779.html?scici=Search~~EditSearch~~1~~top~~~~0"
  },
  {
    "name": "Ribbed Knit Super Crop Tee & Tank Top",
    "price": "17,99",
    "url": "https://eur.shein.com/Ribbed-Knit-Super-Crop-Tee-Tank-Top-p-3012894-cat-1738.html?scici=Search~~EditSearch~~1~~top~~~~0"
  },
  {
    "name": "SHEIN SXY Twist Front Notched Neck Crop Tee",
    "price": "3,99",
    "url": "https://eur.shein.com/SHEIN-SXY-Twist-Front-Notched-Neck-Crop-Tee-p-3153802-cat-2223.html?scici=Search~~EditSearch~~1~~top~~~~0"
  },
  {
    "name": "SHEIN Butterfly-chain Linked Crop Cami Top",
    "price": "5,00",
    "url": "https://eur.shein.com/SHEIN-Butterfly-chain-Linked-Crop-Cami-Top-p-2898727-cat-1779.html?scici=Search~~EditSearch~~1~~top~~~~0"
  },
  {
    "name": "Mock Neck Ruffle Detail Top",
    "price": "6,00",
    "url": "https://eur.shein.com/Mock-Neck-Ruffle-Detail-Top-p-2770797-cat-2223.html?scici=Search~~EditSearch~~1~~top~~~~0"
  },
  {
    "name": "Lace Trim Floral Print Cami Top",
    "price": "4,49 6,00",
    "url": "https://eur.shein.com/Lace-Trim-Floral-Print-Cami-Top-p-6566477-cat-1779.html?scici=Search~~EditSearch~~1~~top~~~~0"
  },
  {
    "name": "SHEIN Lace Up Backless Cami Top",
    "price": "4,00",
    "url": "https://eur.shein.com/SHEIN-Lace-Up-Backless-Cami-Top-p-2433437-cat-1779.html?scici=Search~~EditSearch~~1~~top~~~~0"
  },
  {
    "name": "SHEIN Ruched O-Ring Cutout Self-Tie Halter Crop Top",
    "price": "5,00",
    "url": "https://eur.shein.com/SHEIN-Ruched-O-Ring-Cutout-Self-Tie-Halter-Crop-Top-p-2747120-cat-1779.html?scici=Search~~EditSearch~~1~~top~~~~0"
  },
  {
    "name": "SHEIN Drawstring Front Ditsy Floral Top",
    "price": "3,99",
    "url": "https://eur.shein.com/SHEIN-Drawstring-Front-Ditsy-Floral-Top-p-2006125-cat-1738.html?scici=Search~~EditSearch~~1~~top~~~~0"
  },
  {
    "name": "Contrast Lace Notch Neck Blouse",
    "price": "8,00",
    "url": "https://eur.shein.com/Contrast-Lace-Notch-Neck-Blouse-p-2777623-cat-1733.html?scici=Search~~EditSearch~~1~~top~~~~0"
  },
  {
    "name": "SHEIN Notch Neck Button Front Tank Top",
    "price": "2,99 4,00",
    "url": "https://eur.shein.com/SHEIN-Notch-Neck-Button-Front-Tank-Top-p-1675299-cat-1779.html?scici=Search~~EditSearch~~1~~top~~~~0"
  },
  {
    "name": "Ruffle Armhole Shirred Hem Polka-dot Top",
    "price": "9,00",
    "url": "https://eur.shein.com/Ruffle-Armhole-Shirred-Hem-Polka-dot-Top-p-1455904-cat-1733.html?scici=Search~~EditSearch~~1~~top~~~~0"
  },
  {
    "name": "SHEIN 2pcs Crop Cami Top",
    "price": "7,00",
    "url": "https://eur.shein.com/SHEIN-2pcs-Crop-Cami-Top-p-3013827-cat-1779.html?scici=Search~~EditSearch~~1~~top~~~~0"
  },
  {
    "name": "Fuzzy Panel Crop Tube Top",
    "price": "5,00",
    "url": "https://eur.shein.com/Fuzzy-Panel-Crop-Tube-Top-p-5107542-cat-2223.html?scici=Search~~EditSearch~~1~~top~~~~0"
  },
  {
    "name": "SHEIN V-neck Button Placket Striped Top",
    "price": "5,99",
    "url": "https://eur.shein.com/SHEIN-V-neck-Button-Placket-Striped-Top-p-1455209-cat-1738.html?scici=Search~~EditSearch~~1~~top~~~~0"
  },
  {
    "name": "SHEIN Love Graphic Camo Print Crop Top",
    "price": "4,00",
    "url": "https://eur.shein.com/SHEIN-Love-Graphic-Camo-Print-Crop-Top-p-745068-cat-1779.html?scici=Search~~EditSearch~~1~~top~~~~0"
  },
  {
    "name": "SHEIN Solid Rib-knit Tank Top",
    "price": "4,00",
    "url": "https://eur.shein.com/SHEIN-Solid-Rib-knit-Tank-Top-p-1357749-cat-1779.html?scici=Search~~EditSearch~~1~~top~~~~0"
  },
  {
    "name": "SHEIN BASICS Solid Crop Halter Top",
    "price": "5,00",
    "url": "https://eur.shein.com/SHEIN-BASICS-Solid-Crop-Halter-Top-p-1550205-cat-1779.html?scici=Search~~EditSearch~~1~~top~~~~0"
  },
  {
    "name": "Tie Back Lettuce Trim Crop Top",
    "price": "12,99",
    "url": "https://eur.shein.com/Tie-Back-Lettuce-Trim-Crop-Top-p-6516882-cat-1738.html?scici=Search~~EditSearch~~1~~top~~~~0"
  },
  {
    "name": "SHEIN Marble Print Tie Back Crop Halter Top",
    "price": "5,00",
    "url": "https://eur.shein.com/SHEIN-Marble-Print-Tie-Back-Crop-Halter-Top-p-2902040-cat-1779.html?scici=Search~~EditSearch~~1~~top~~~~0"
  },
  {
    "name": "DAZY Raglan Sleeve Super Crop Tee Without Crop Top",
    "price": "3,99",
    "url": "https://eur.shein.com/DAZY-Raglan-Sleeve-Super-Crop-Tee-Without-Crop-Top-p-6664782-cat-1738.html?scici=Search~~EditSearch~~1~~top~~~~0"
  },
  {
    "name": "SHEIN Rib-knit Tie Dye Crop Tank Top",
    "price": "4,00",
    "url": "https://eur.shein.com/SHEIN-Rib-knit-Tie-Dye-Crop-Tank-Top-p-1379037-cat-1779.html?scici=Search~~EditSearch~~1~~top~~~~0"
  },
  {
    "name": "SHEIN Graphic Print Crop Cami Top",
    "price": "4,00",
    "url": "https://eur.shein.com/SHEIN-Graphic-Print-Crop-Cami-Top-p-2288830-cat-1779.html?scici=Search~~EditSearch~~1~~top~~~~0"
  },
  {
    "name": "SHEIN Square Neck Fitted Top",
    "price": "5,99",
    "url": "https://eur.shein.com/SHEIN-Square-Neck-Fitted-Top-p-1848934-cat-1738.html?scici=Search~~EditSearch~~1~~top~~~~0"
  },
  {
    "name": "Allover Print Tie Back Puff Sleeve Blouse",
    "price": "11,00",
    "url": "https://eur.shein.com/Allover-Print-Tie-Back-Puff-Sleeve-Blouse-p-5043412-cat-1733.html?scici=Search~~EditSearch~~1~~top~~~~0"
  },
  {
    "name": "Plunge Neck Crisscross Back Crop Tank Top",
    "price": "5,00",
    "url": "https://eur.shein.com/Plunge-Neck-Crisscross-Back-Crop-Tank-Top-p-3323949-cat-1779.html?scici=Search~~EditSearch~~1~~top~~~~0"
  },
  {
    "name": "SHEIN Butterfly Sleeve Tie Front Top",
    "price": "9,00",
    "url": "https://eur.shein.com/SHEIN-Butterfly-Sleeve-Tie-Front-Top-p-3096177-cat-2223.html?scici=Search~~EditSearch~~1~~top~~~~0"
  },
  {
    "name": "Backless Knotted Ruffle Hem Halter Top",
    "price": "7,00",
    "url": "https://eur.shein.com/Backless-Knotted-Ruffle-Hem-Halter-Top-p-2394889-cat-1779.html?scici=Search~~EditSearch~~1~~top~~~~0"
  },
  {
    "name": "SHEIN Tie Hem Butterfly Print Cami Crop Top",
    "price": "4,00",
    "url": "https://eur.shein.com/SHEIN-Tie-Hem-Butterfly-Print-Cami-Crop-Top-p-5755692-cat-1779.html?scici=Search~~EditSearch~~1~~top~~~~0"
  },
  {
    "name": "Tie Dye Triangle Halter Bikini Top",
    "price": "5,00",
    "url": "https://eur.shein.com/Tie-Dye-Triangle-Halter-Bikini-Top-p-1022078-cat-2291.html?scici=Search~~RecommendList~~RS_emarsys,RJ_NoFaultTolerant~~Recommendations%20For%20You~~SPcSearchResultRecommendationsForYou~~0"
  },
  {
    "name": "Ring Linked Bikini Top",
    "price": "6,00",
    "url": "https://eur.shein.com/Ring-Linked-Bikini-Top-p-1027860-cat-2291.html?scici=Search~~RecommendList~~RS_emarsys,RJ_NoFaultTolerant~~Recommendations%20For%20You~~SPcSearchResultRecommendationsForYou~~0"
  },
  {
    "name": "Tie Back Triangle Bikini Top",
    "price": "5,00",
    "url": "https://eur.shein.com/Tie-Back-Triangle-Bikini-Top-p-1051194-cat-2291.html?scici=Search~~RecommendList~~RS_emarsys,RJ_NoFaultTolerant~~Recommendations%20For%20You~~SPcSearchResultRecommendationsForYou~~0"
  },
  {
    "name": "SHEIN Lace Trim Hook and Eye Front Bustier Cami Top",
    "price": "5,49 7,00",
    "url": "https://eur.shein.com/Lace-Trim-Hook-and-Eye-Front-Bustier-Cami-Top-p-1054047-cat-1779.html?scici=Search~~RecommendList~~RS_emarsys,RJ_NoFaultTolerant~~Recommendations%20For%20You~~SPcSearchResultRecommendationsForYou~~0"
  },
  {
    "name": "SHEIN Lettuce Trim Butterfly Embroidery Crop Top",
    "price": "5,99",
    "url": "https://eur.shein.com/Lettuce-Trim-Butterfly-Embroidery-Crop-Top-p-1056173-cat-1738.html?scici=Search~~RecommendList~~RS_emarsys,RJ_NoFaultTolerant~~Recommendations%20For%20You~~SPcSearchResultRecommendationsForYou~~0"
  },
  {
    "name": "",
    "price": "",
    "url": "https://eur.shein.com/Frill-Trim-Shirred-Tube-Top-p-1075984-cat-2223.html?scici=Search~~RecommendList~~RS_emarsys,RJ_NoFaultTolerant~~Recommendations%20For%20You~~SPcSearchResultRecommendationsForYou~~0"
  },
  {
    "name": "",
    "price": "",
    "url": "https://eur.shein.com/Crop-Criss-Cross-Halter-Top-p-1095835-cat-1779.html?scici=Search~~RecommendList~~RS_emarsys,RJ_NoFaultTolerant~~Recommendations%20For%20You~~SPcSearchResultRecommendationsForYou~~0"
  },
  {
    "name": "",
    "price": "",
    "url": "https://eur.shein.com/Lace-Up-Backless-Solid-Cami-Top-p-1107921-cat-1779.html?scici=Search~~RecommendList~~RS_emarsys,RJ_NoFaultTolerant~~Recommendations%20For%20You~~SPcSearchResultRecommendationsForYou~~0"
  },
  {
    "name": "",
    "price": "",
    "url": "https://eur.shein.com/Tied-Open-Back-Crop-Halter-Top-p-1113766-cat-1779.html?scici=Search~~RecommendList~~RS_emarsys,RJ_NoFaultTolerant~~Recommendations%20For%20You~~SPcSearchResultRecommendationsForYou~~0"
  },
  {
    "name": "",
    "price": "",
    "url": "https://eur.shein.com/Solid-Crisscross-Self-Tie-Crop-Top-p-1125193-cat-2223.html?scici=Search~~RecommendList~~RS_emarsys,RJ_NoFaultTolerant~~Recommendations%20For%20You~~SPcSearchResultRecommendationsForYou~~0"
  },
  {
    "name": "",
    "price": "",
    "url": "https://eur.shein.com/Drawstring-Front-Bikini-Top-p-1151505-cat-2291.html?scici=Search~~RecommendList~~RS_emarsys,RJ_NoFaultTolerant~~Recommendations%20For%20You~~SPcSearchResultRecommendationsForYou~~0"
  },
  {
    "name": "",
    "price": "",
    "url": "https://eur.shein.com/One-Shoulder-Rib-knit-Crop-Top-p-1179502-cat-2223.html?scici=Search~~RecommendList~~RS_emarsys,RJ_NoFaultTolerant~~Recommendations%20For%20You~~SPcSearchResultRecommendationsForYou~~0"
  },
  {
    "name": "",
    "price": "",
    "url": "https://eur.shein.com/V-Neck-Bikini-Top-p-1224571-cat-2291.html?scici=Search~~RecommendList~~RS_emarsys,RJ_NoFaultTolerant~~Recommendations%20For%20You~~SPcSearchResultRecommendationsForYou~~0"
  },
  {
    "name": "",
    "price": "",
    "url": "https://eur.shein.com/Ditsy-Floral-Crop-Cami-Top-p-1255652-cat-1779.html?scici=Search~~RecommendList~~RS_emarsys,RJ_NoFaultTolerant~~Recommendations%20For%20You~~SPcSearchResultRecommendationsForYou~~0"
  },
  {
    "name": "",
    "price": "",
    "url": "https://eur.shein.com/Girls-Ribbed-Butterfly-Graphic-Cropped-Cami-Top-p-1259509-cat-2830.html?scici=Search~~RecommendList~~RS_emarsys,RJ_NoFaultTolerant~~Recommendations%20For%20You~~SPcSearchResultRecommendationsForYou~~0"
  },
  {
    "name": "",
    "price": "",
    "url": "https://eur.shein.com/Ditsy-Floral-Self-Tie-Surplice-Wrap-Top-p-1263954-cat-1733.html?scici=Search~~RecommendList~~RS_emarsys,RJ_NoFaultTolerant~~Recommendations%20For%20You~~SPcSearchResultRecommendationsForYou~~0"
  },
  {
    "name": "",
    "price": "",
    "url": "https://eur.shein.com/Contrast-Neck-Rainbow-Striped-Top-p-1269973-cat-1738.html?scici=Search~~RecommendList~~RS_emarsys,RJ_NoFaultTolerant~~Recommendations%20For%20You~~SPcSearchResultRecommendationsForYou~~0"
  },
  {
    "name": "",
    "price": "",
    "url": "https://eur.shein.com/Dalmatian-Cut-out-One-Shoulder-Bikini-Top-p-1276425-cat-2291.html?scici=Search~~RecommendList~~RS_emarsys,RJ_NoFaultTolerant~~Recommendations%20For%20You~~SPcSearchResultRecommendationsForYou~~0"
  },
  {
    "name": "",
    "price": "",
    "url": "https://eur.shein.com/Tie-Dye-Lace-Up-Back-Cami-Top-p-1287181-cat-1779.html?scici=Search~~RecommendList~~RS_emarsys,RJ_NoFaultTolerant~~Recommendations%20For%20You~~SPcSearchResultRecommendationsForYou~~0"
  },
  {
    "name": "",
    "price": "",
    "url": "https://eur.shein.com/Letter-Graphic-Crop-Cami-Top-p-1309778-cat-1779.html?scici=Search~~RecommendList~~RS_emarsys,RJ_NoFaultTolerant~~Recommendations%20For%20You~~SPcSearchResultRecommendationsForYou~~0"
  },
  {
    "name": "",
    "price": "",
    "url": "https://eur.shein.com/Button-Half-Placket-Rib-knit-Tank-Top-p-1344153-cat-1779.html?scici=Search~~RecommendList~~RS_emarsys,RJ_NoFaultTolerant~~Recommendations%20For%20You~~SPcSearchResultRecommendationsForYou~~0"
  },
  {
    "name": "",
    "price": "",
    "url": "https://eur.shein.com/Contrast-Striped-Letter-Graphic-Top-p-1347625-cat-1733.html?scici=Search~~RecommendList~~RS_emarsys,RJ_NoFaultTolerant~~Recommendations%20For%20You~~SPcSearchResultRecommendationsForYou~~0"
  },
  {
    "name": "",
    "price": "",
    "url": "https://eur.shein.com/Button-Front-Crop-Top-p-1351151-cat-1738.html?scici=Search~~RecommendList~~RS_emarsys,RJ_NoFaultTolerant~~Recommendations%20For%20You~~SPcSearchResultRecommendationsForYou~~0"
  },
  {
    "name": "",
    "price": "",
    "url": "https://eur.shein.com/Notch-Neck-Lettuce-Edge-Rib-knit-Tank-Top-p-1353755-cat-1779.html?scici=Search~~RecommendList~~RS_emarsys,RJ_NoFaultTolerant~~Recommendations%20For%20You~~SPcSearchResultRecommendationsForYou~~0"
  },
  {
    "name": "",
    "price": "",
    "url": "https://eur.shein.com/Crop-Cami-Top-p-1364455-cat-1779.html?scici=Search~~RecommendList~~RS_emarsys,RJ_NoFaultTolerant~~Recommendations%20For%20You~~SPcSearchResultRecommendationsForYou~~0"
  }
]